README.rst
setup.py
pysie/__init__.py
pysie.egg-info/PKG-INFO
pysie.egg-info/SOURCES.txt
pysie.egg-info/dependency_links.txt
pysie.egg-info/not-zip-safe
pysie.egg-info/requires.txt
pysie.egg-info/top_level.txt